{
  "m_GameObject": {
    "m_FileID": 0,
    "m_PathID": -8362682507488640628
  },
  "m_Enabled": 1,
  "m_Script": {
    "m_FileID": 0,
    "m_PathID": -1126231878297564127
  },
  "m_Name": "",
  "_scale": 0.95,
  "_shadowImage": {
    "m_FileID": 0,
    "m_PathID": 2546306041624642786
  },
  "_indexRecttrans": {
    "m_FileID": 0,
    "m_PathID": -4848725240114365149
  },
  "_indexText": {
    "m_FileID": 0,
    "m_PathID": 5886142429084595943
  },
  "_isOverrideIndexPosY": 0,
  "_overrideIndexPosY": 100.0,
  "_offsetZ": 0.5,
  "_shadowScale": 4.0
}